deno/__init__.py
deno/__main__.py
deno/_find_deno.py
deno-2.6.7.data/scripts/deno.exe
deno-2.6.7.dist-info/METADATA
deno-2.6.7.dist-info/WHEEL
deno-2.6.7.dist-info/licenses/LICENSE
deno-2.6.7.dist-info/RECORD
