Metadata-Version: 2.4
Name: deno
Version: 2.6.7
Summary: Python redistribution of Deno binaries
Author-email: Trevor Manz <trevor.j.manz@gmail.com>
License-Expression: MIT
License-File: LICENSE
Requires-Python: >=3.10
